odoo9_addon_openeducat_library-9.0.2.4.0-py2.7-nspkg.pth
odoo9_addon_openeducat_library-9.0.2.4.0.dist-info/top_level.txt
odoo9_addon_openeducat_library-9.0.2.4.0.dist-info/WHEEL
odoo9_addon_openeducat_library-9.0.2.4.0.dist-info/RECORD
odoo9_addon_openeducat_library-9.0.2.4.0.dist-info/metadata.json
odoo9_addon_openeducat_library-9.0.2.4.0.dist-info/DESCRIPTION.rst
odoo9_addon_openeducat_library-9.0.2.4.0.dist-info/METADATA
odoo9_addon_openeducat_library-9.0.2.4.0.dist-info/namespace_packages.txt
odoo_addons/openeducat_library/book_queue_sequence.xml
odoo_addons/openeducat_library/__openerp__.py
odoo_addons/openeducat_library/__init__.py
odoo_addons/openeducat_library/security/library_security.xml
odoo_addons/openeducat_library/security/ir.model.access.csv
odoo_addons/openeducat_library/report/report_student_library_card.py
odoo_addons/openeducat_library/report/report_student_library_card.xml
odoo_addons/openeducat_library/report/report_book_barcode.xml
odoo_addons/openeducat_library/report/__init__.py
odoo_addons/openeducat_library/report/report_book_barcode.py
odoo_addons/openeducat_library/report/report_menu.xml
odoo_addons/openeducat_library/dashboard/librarian_dashboard_view.xml
odoo_addons/openeducat_library/models/book_queue.py
odoo_addons/openeducat_library/models/book.py
odoo_addons/openeducat_library/models/book_purchase.py
odoo_addons/openeducat_library/models/library.py
odoo_addons/openeducat_library/models/book_unit.py
odoo_addons/openeducat_library/models/tag.py
odoo_addons/openeducat_library/models/book_movement.py
odoo_addons/openeducat_library/models/__init__.py
odoo_addons/openeducat_library/models/student.py
odoo_addons/openeducat_library/models/faculty.py
odoo_addons/openeducat_library/models/author.py
odoo_addons/openeducat_library/models/publisher.py
odoo_addons/openeducat_library/i18n/openeducat_library.pot
odoo_addons/openeducat_library/menus/library_menu.xml
odoo_addons/openeducat_library/views/book_purchase_view.xml
odoo_addons/openeducat_library/views/book_view.xml
odoo_addons/openeducat_library/views/book_queue_view.xml
odoo_addons/openeducat_library/views/book_movement_view.xml
odoo_addons/openeducat_library/views/student_view.xml
odoo_addons/openeducat_library/views/library_view.xml
odoo_addons/openeducat_library/views/faculty_view.xml
odoo_addons/openeducat_library/views/publisher_view.xml
